LICENSE
MANIFEST.in
README.md
setup.py
Dictionary/Dictionary.c
Dictionary/Dictionary.pxd
Dictionary/Dictionary.pyx
Dictionary/ExceptionalWord.c
Dictionary/ExceptionalWord.pxd
Dictionary/ExceptionalWord.pyx
Dictionary/Pos.py
Dictionary/TxtDictionary.c
Dictionary/TxtDictionary.pxd
Dictionary/TxtDictionary.pyx
Dictionary/TxtWord.c
Dictionary/TxtWord.pxd
Dictionary/TxtWord.pyx
Dictionary/VectorizedDictionary.c
Dictionary/VectorizedDictionary.pxd
Dictionary/VectorizedDictionary.pyx
Dictionary/VectorizedWord.c
Dictionary/VectorizedWord.pxd
Dictionary/VectorizedWord.pyx
Dictionary/Word.c
Dictionary/Word.pxd
Dictionary/Word.pyx
Dictionary/__init__.py
Dictionary/Trie/Trie.c
Dictionary/Trie/Trie.pxd
Dictionary/Trie/Trie.pyx
Dictionary/Trie/TrieNode.c
Dictionary/Trie/TrieNode.pxd
Dictionary/Trie/TrieNode.pyx
Dictionary/Trie/__init__.py
Dictionary/data/__init__.py
Dictionary/data/turkish_dictionary.txt
Dictionary/data/turkish_misspellings.txt
Dictionary/data/turkish_morphological_lexicon.txt
Language/EnglishLanguage.c
Language/EnglishLanguage.pxd
Language/EnglishLanguage.pyx
Language/Language.c
Language/Language.pxd
Language/Language.pyx
Language/TurkishLanguage.c
Language/TurkishLanguage.pxd
Language/TurkishLanguage.pyx
Language/__init__.py
NlpToolkit_Dictionary_Cy.egg-info/PKG-INFO
NlpToolkit_Dictionary_Cy.egg-info/SOURCES.txt
NlpToolkit_Dictionary_Cy.egg-info/dependency_links.txt
NlpToolkit_Dictionary_Cy.egg-info/requires.txt
NlpToolkit_Dictionary_Cy.egg-info/top_level.txt
Syllibification/Syllable.c
Syllibification/Syllable.pxd
Syllibification/Syllable.pyx
Syllibification/SyllableList.c
Syllibification/SyllableList.pyx
Syllibification/__init__.py
nlptoolkit_dictionary_cy.egg-info/PKG-INFO
nlptoolkit_dictionary_cy.egg-info/SOURCES.txt
nlptoolkit_dictionary_cy.egg-info/dependency_links.txt
nlptoolkit_dictionary_cy.egg-info/requires.txt
nlptoolkit_dictionary_cy.egg-info/top_level.txt