Metadata-Version: 2.4
Name: nlptoolkit-dictionary-cy
Version: 1.0.34
Summary: Simple Dictionary Processing
Home-page: https://github.com/StarlangSoftware/Dictionary-Cy
Author: olcaytaner
Author-email: olcay.yildiz@ozyegin.edu.tr
License-File: LICENSE
Requires-Dist: NlpToolkit-Math-Cy
Requires-Dist: NlpToolkit-Util-Cy
Dynamic: author
Dynamic: author-email
Dynamic: description
Dynamic: description-content-type
Dynamic: home-page
Dynamic: license-file
Dynamic: requires-dist
Dynamic: summary
